pypulsar/__init__.py
pypulsar/__main__.py
pypulsar/acl.py
pypulsar/cli.py
pypulsar/engine.py
pypulsar/window_manager.py
pypulsar/ipc/__init__.py
pypulsar/ipc/api.py
pypulsar/plugins/__init__.py
pypulsar/plugins/plugin_manager.py
pypulsar/templates/basic/main.py
pypulsar/templates/basic/requirements.txt
pypulsar/templates/basic/web/index.html
pypulsar-0.1.2.dist-info/licenses/LICENSE
pypulsar-0.1.2.dist-info/METADATA
pypulsar-0.1.2.dist-info/WHEEL
pypulsar-0.1.2.dist-info/entry_points.txt
pypulsar-0.1.2.dist-info/top_level.txt
pypulsar-0.1.2.dist-info/RECORD
