Metadata-Version: 2.4
Name: pypulsar
Version: 0.1.2
Summary: Modern Python desktop framework – lightweight, secure, beautiful
Author-email: dannyx-hub <daro322.dp@gmail.com>
License-Expression: MIT
Project-URL: Homepage, https://github.com/dannyx-hub/pyphoton
Project-URL: Documentation, https://pyphoton.dev
Project-URL: Repository, https://github.com/dannyx-hub/pyphoton
Project-URL: Issues, https://github.com/dannyx-hub/pyphoton/issues
Keywords: desktop,gui,pywebview,framework,electron-alternative
Classifier: Development Status :: 5 - Production/Stable
Classifier: Intended Audience :: Developers
Classifier: Programming Language :: Python :: 3
Classifier: Programming Language :: Python :: 3.9
Classifier: Programming Language :: Python :: 3.10
Classifier: Programming Language :: Python :: 3.11
Classifier: Programming Language :: Python :: 3.12
Classifier: Programming Language :: Python :: 3.13
Classifier: Topic :: Software Development :: Libraries :: Application Frameworks
Classifier: Operating System :: MacOS
Classifier: Operating System :: Microsoft :: Windows
Classifier: Operating System :: POSIX :: Linux
Requires-Python: >=3.9
License-File: LICENSE
Requires-Dist: pywebview>=5.1
Requires-Dist: aiohttp>=3.9.0
Requires-Dist: typer[all]>=0.12.0
Requires-Dist: requests==2.32.5
Provides-Extra: dev
Requires-Dist: watchgod>=0.8; extra == "dev"
Requires-Dist: rich>=13.0; extra == "dev"
Provides-Extra: build
Requires-Dist: pyinstaller>=6.0; extra == "build"
Dynamic: license-file
